qbee_gpio/__init__.py
qbee_gpio/config.py
qbee_gpio/gpio/__init__.py
qbee_gpio/gpio/lcd_display.py
qbee_gpio/gpio/setup.py
qbee_gpio/gpio/switch.py
qbee_gpio/gpio/types.py
qbee_gpio/metadata/__init__.py
qbee_gpio/metadata/interface.py
qbee_gpio/metadata/librespot.py
qbee_gpio/metadata/model.py
qbee_gpio/metadata/pipe_reader.py
qbee_gpio/metadata/shairport.py
qbee_gpio/orchestrator.py
qbee_gpio/py.typed
qbee_gpio/sound_poller.py
qbee_gpio-3.0.2.dist-info/LICENSE
qbee_gpio-3.0.2.dist-info/METADATA
qbee_gpio-3.0.2.dist-info/WHEEL
qbee_gpio-3.0.2.dist-info/entry_points.txt
qbee_gpio-3.0.2.dist-info/RECORD
