Metadata-Version: 2.1
Name: qbee-gpio
Version: 3.0.2
Summary: Control an LCD display and amplifier relay for use in an AirPlay and/or Spotify Connect Raspberry Pi server.
Home-page: https://github.com/gpajot/qbee-gpio
License: MIT
Author: Gabriel Pajot
Author-email: gab@lescactus.eu
Requires-Python: >=3.8
Classifier: License :: OSI Approved :: MIT License
Classifier: Programming Language :: Python :: 3
Classifier: Programming Language :: Python :: 3.8
Classifier: Programming Language :: Python :: 3.9
Classifier: Programming Language :: Python :: 3.10
Classifier: Programming Language :: Python :: 3.11
Classifier: Programming Language :: Python :: 3.12
Requires-Dist: asyncinotify (>=4.0,<4.1) ; python_version < "4"
Requires-Dist: concurrent-tasks (>=1.7,<2)
Requires-Dist: zenconfig[attrs,yaml] (>=2.1.0,<3)
Project-URL: Repository, https://github.com/gpajot/qbee-gpio
